[
  {
    "image": "full-ms2.jpg",
    "category": "Entreprise",
    "description": "Identité visuelle et charte graphique complète."
  },
  {
    "image": "full-h.jpg",
    "category": "Entreprise",
    "description": "Conception de support de communication print."
  },
  {
    "image": "inv.jpg",
    "category": "Entreprise",
    "description": "Design d'invitation pour évènement corporate."
  },
  {
    "image": "portfolio.jpeg",
    "category": "Entreprise",
    "description": "Maquette UI pour portfolio professionnel."
  },
  {
    "image": "full-6pages2.jpg",
    "category": "Entreprise",
    "description": "Brochure de présentation 6 pages."
  },
  {
    "image": "info.jpg",
    "category": "Entreprise",
    "description": "Infographie pédagogique pour rapports."
  },
  {
    "image": "full-mars.jpg",
    "category": "Entreprise",
    "description": "Campagne visuelle thématique."
  },
  {
    "image": "maquettes2.jpg",
    "category": "Entreprise",
    "description": "Série de maquettes pour application mobile."
  },
  {
    "image": "sedd3.jpg",
    "category": "Entreprise",
    "description": "Visuels pour réseaux sociaux d'entreprise."
  },
  {
    "image": "portfolio (1).jpeg",
    "category": "Entreprise",
    "description": "Déclinaison de l'identité sur supports variés."
  },
  {
    "image": "bookUTP-v1v2.jpg",
    "category": "Entreprise",
    "description": "Design de couverture de livre blanc."
  },
  {
    "image": "bleu.jpg",
    "category": "Entreprise",
    "description": "Recherche graphique sur la colorimétrie."
  },
  {
    "image": "sedd2.png",
    "category": "Entreprise",
    "description": "Illustration vectorielle pour site web."
  },
  {
    "image": "maquettes11.jpg",
    "category": "Entreprise",
    "description": "Prototype haute fidélité d'interface."
  },
  {
    "image": "SalesEvent2019.jpg",
    "category": "Entreprise",
    "description": "Affiche pour évènement commercial."
  },
  {
    "image": "full-tennisstat.jpg",
    "category": "Création",
    "description": "Dashboard de statistiques sportives."
  },
  {
    "image": "portfolio (2).jpeg",
    "category": "Création",
    "description": "Exploration créative de mise en page."
  },
  {
    "image": "full-NadalMoon.jpg",
    "category": "Création",
    "description": "Composition digitale thématique."
  },
  {
    "image": "1.jpg",
    "category": "Création",
    "description": "Concept art et expérimentation visuelle."
  },
  {
    "image": "_DSC1998-copie-3.jpeg",
    "category": "Création",
    "description": "Retouche photo créative et montage."
  },
  {
    "image": "2-light.jpg",
    "category": "Création",
    "description": "Travail sur les jeux de lumière."
  },
  {
    "image": "full-etpourqq.PNG",
    "category": "Création",
    "description": "Typographie et mise en mouvement."
  },
  {
    "image": "1-rouge-light.jpg",
    "category": "Création",
    "description": "Variation chromatique et ambiance."
  },
  {
    "image": "full-yt.jpg",
    "category": "Création",
    "description": "Design de miniatures pour YouTube."
  },
  {
    "image": "2-light-2.jpg",
    "category": "Création",
    "description": "Abstractions visuelles et contrastes."
  },
  {
    "image": "2-light-1.jpg",
    "category": "Création",
    "description": "Série graphique sur la luminescence."
  }
]